{
  "project_info": {
    "project_number": "1036460481247",
    "project_id": "ecoeducation-2966a",
    "storage_bucket": "ecoeducation-2966a.firebasestorage.app"
  },
  "client": [
    {
      "client_info": {
        "mobilesdk_app_id": "1:1036460481247:android:5facf388cd4127793ee76a",
        "android_client_info": {
          "package_name": "my.com.a221491_amiraizatbinharith_nelson_project2"
        }
      },
      "oauth_client": [],
      "api_key": [
        {
          "current_key": "AIzaSyAurP91d2bbxcw5jyE8jwC151yC-rPidM4"
        }
      ],
      "services": {
        "appinvite_service": {
          "other_platform_oauth_client": []
        }
      }
    }
  ],
  "configuration_version": "1"
}